tracing/__init__.py
tracing/decorators.py
tracing/hooks.py
tracing/implementation_otel_hooks.py
tracing/utils.py
tracing/tracers/__init__.py
tracing/tracers/jaeger.py
otel_hooks_implement_django_instrument-0.0.2.dist-info/METADATA
otel_hooks_implement_django_instrument-0.0.2.dist-info/WHEEL
otel_hooks_implement_django_instrument-0.0.2.dist-info/top_level.txt
otel_hooks_implement_django_instrument-0.0.2.dist-info/RECORD
